beta_test_version_powerhouse_helper_a1-1.0.0.data/data/test_version_powerhouse_helper/GameGooseKiller/Game_goose.py
beta_test_version_powerhouse_helper_a1-1.0.0.data/data/test_version_powerhouse_helper/GameGooseKiller/font/UA Propisi.ttf
beta_test_version_powerhouse_helper_a1-1.0.0.data/data/test_version_powerhouse_helper/GameGooseKiller/image/Farm-Goose.ico
beta_test_version_powerhouse_helper_a1-1.0.0.data/data/test_version_powerhouse_helper/GameGooseKiller/image/background.png
beta_test_version_powerhouse_helper_a1-1.0.0.data/data/test_version_powerhouse_helper/GameGooseKiller/image/bonus.png
beta_test_version_powerhouse_helper_a1-1.0.0.data/data/test_version_powerhouse_helper/GameGooseKiller/image/boom.png
beta_test_version_powerhouse_helper_a1-1.0.0.data/data/test_version_powerhouse_helper/GameGooseKiller/image/enemy.png
beta_test_version_powerhouse_helper_a1-1.0.0.data/data/test_version_powerhouse_helper/GameGooseKiller/image/gameover.png
beta_test_version_powerhouse_helper_a1-1.0.0.data/data/test_version_powerhouse_helper/GameGooseKiller/image/Goose/1-1.png
beta_test_version_powerhouse_helper_a1-1.0.0.data/data/test_version_powerhouse_helper/GameGooseKiller/image/Goose/1-2.png
beta_test_version_powerhouse_helper_a1-1.0.0.data/data/test_version_powerhouse_helper/GameGooseKiller/image/Goose/1-3.png
beta_test_version_powerhouse_helper_a1-1.0.0.data/data/test_version_powerhouse_helper/GameGooseKiller/image/Goose/1-4.png
beta_test_version_powerhouse_helper_a1-1.0.0.data/data/test_version_powerhouse_helper/GameGooseKiller/image/Goose/1-5.png
beta_test_version_powerhouse_helper_a1-1.0.0.data/data/test_version_powerhouse_helper/GameGooseKiller/image/background/1-1.png
beta_test_version_powerhouse_helper_a1-1.0.0.data/data/test_version_powerhouse_helper/GameGooseKiller/image/background/1-2.png
beta_test_version_powerhouse_helper_a1-1.0.0.data/data/test_version_powerhouse_helper/GameGooseKiller/image/background/1-3.png
beta_test_version_powerhouse_helper_a1-1.0.0.dist-info/LICENSE
beta_test_version_powerhouse_helper_a1-1.0.0.dist-info/METADATA
beta_test_version_powerhouse_helper_a1-1.0.0.dist-info/WHEEL
beta_test_version_powerhouse_helper_a1-1.0.0.dist-info/entry_points.txt
beta_test_version_powerhouse_helper_a1-1.0.0.dist-info/top_level.txt
beta_test_version_powerhouse_helper_a1-1.0.0.dist-info/RECORD
